{
  "signedContributors": [
    {
      "name": "rishiraj",
      "id": 44090649,
      "comment_id": 2170578748,
      "created_at": "2024-06-15T19:31:20Z",
      "repoId": 741297064,
      "pullRequestNo": 135
    },
    {
      "name": "mmacvicar",
      "id": 59354,
      "comment_id": 2236493182,
      "created_at": "2024-07-18T13:17:43Z",
      "repoId": 741297064,
      "pullRequestNo": 152
    },
    {
      "name": "jimexist",
      "id": 622789,
      "comment_id": 2255151376,
      "created_at": "2024-07-29T07:23:55Z",
      "repoId": 741297064,
      "pullRequestNo": 160
    },
    {
      "name": "michaeldriscoll-avant",
      "id": 85255083,
      "comment_id": 2259143427,
      "created_at": "2024-07-30T20:21:33Z",
      "repoId": 741297064,
      "pullRequestNo": 161
    },
    {
      "name": "EdoardoPona",
      "id": 29152472,
      "comment_id": 2271115922,
      "created_at": "2024-08-06T11:58:00Z",
      "repoId": 741297064,
      "pullRequestNo": 167
    },
    {
      "name": "hidenori-endo",
      "id": 15546605,
      "comment_id": 2307217499,
      "created_at": "2024-08-23T14:31:17Z",
      "repoId": 741297064,
      "pullRequestNo": 182
    }
  ]
}